{
    "type": "spacing",
    "p-0": {"value": "{0}"},
    "p-px": {"value": "{1}"},
    "p-0-5": {"value": "{2}"},
    "p-1": {"value": "{4}"},
    "p-1-5": {"value": "{6}"},
    "p-2": {"value": "{8}"},
    "p-3": {"value": "{12}"},
    "p-4": {"value": "{16}"},
    "p-5": {"value": "{20}"},
    "p-6": {"value": "{24}"},
    "p-7": {"value": "{28}"},
    "p-8": {"value": "{32}"},
    "p-9": {"value": "{36}"},
    "p-10": {"value": "{40}"},
    "p-11": {"value": "{44}"},
    "p-12": {"value": "{48}"},
    "p-13": {"value": "{52}"},
    "p-14": {"value": "{56}"},
    "p-15": {"value": "{60}"},
    "p-16": {"value": "{64}"},
    "p-17": {"value": "{68}"},
    "p-18": {"value": "{72}"},
    "p-19": {"value": "{76}"},
    "p-20": {"value": "{80}"},
    "p-22": {"value": "{88}"},
    "p-24": {"value": "{96}"},
    "p-28": {"value": "{112}"},
    "p-30": {"value": "{120}"},

    "m-0": {"value": "{0}"},
    "m-px": {"value": "{1}"},
    "m-0-5": {"value": "{2}"},
    "m-1": {"value": "{4}"},
    "m-1-5": {"value": "{6}"},
    "m-2": {"value": "{8}"},
    "m-3": {"value": "{12}"},
    "m-4": {"value": "{16}"},
    "m-5": {"value": "{20}"},
    "m-6": {"value": "{24}"},
    "m-7": {"value": "{28}"},
    "m-8": {"value": "{32}"},
    "m-9": {"value": "{36}"},
    "m-10": {"value": "{40}"},
    "m-11": {"value": "{44}"},
    "m-12": {"value": "{48}"},
    "m-13": {"value": "{52}"},
    "m-14": {"value": "{56}"},
    "m-15": {"value": "{60}"},
    "m-16": {"value": "{64}"},
    "m-17": {"value": "{68}"},
    "m-18": {"value": "{72}"},
    "m-19": {"value": "{76}"},
    "m-20": {"value": "{80}"},
    "m-22": {"value": "{88}"},
    "m-24": {"value": "{96}"},
    "m-28": {"value": "{112}"},
    "m-30": {"value": "{120}"}

}

